pyrouting/__init__.py
pyrouting/mobility/__init__.py
pyrouting/mobility/src/__init__.py
pyrouting/mobility/src/data.py
pyrouting/mobility/src/errors.py
pyrouting/mobility/src/utils.py
pyrouting/mobility/tests/__init__.py
pyrouting/mobility_data_routing.egg-info/dependency_links.txt
pyrouting/mobility_data_routing.egg-info/PKG-INFO
pyrouting/mobility_data_routing.egg-info/requires.txt
pyrouting/mobility_data_routing.egg-info/SOURCES.txt
pyrouting/mobility_data_routing.egg-info/top_level.txt
pyrouting/README.md
pyrouting/router/__init__.py
pyrouting/router/src/__init__.py
pyrouting/router/src/network.py
pyrouting/router/src/router.py
pyrouting/router/src/utils.py
pyrouting/router/test/__init__.py
pyrouting-0.1.5.dist-info/LICENSE
pyrouting-0.1.5.dist-info/METADATA
pyrouting-0.1.5.dist-info/WHEEL
pyrouting-0.1.5.dist-info/RECORD
